CONTRIBUTORS.rst
MANIFEST.in
README.rst
setup.py
buildout/__init__.py
buildout.requirements.egg-info/PKG-INFO
buildout.requirements.egg-info/SOURCES.txt
buildout.requirements.egg-info/dependency_links.txt
buildout.requirements.egg-info/entry_points.txt
buildout.requirements.egg-info/namespace_packages.txt
buildout.requirements.egg-info/not-zip-safe
buildout.requirements.egg-info/requires.txt
buildout.requirements.egg-info/top_level.txt
buildout/dumprequirements/__init__.py
buildout/requirements/__init__.py