Metadata-Version: 1.1
Name: buildout.requirements
Version: 0.2.1
Summary: Dump buildout picked versions as a pip compatible requirements.txt file. Fork of buildout.dumprequirements.
Home-page: https://github.com/liqd/buildout.requirements
Author: Yves Müller
Author-email: yves.mueller@liqd.de
License: GPL
Keywords: buildout extension dump picked versions requirements.txt
Platform: UNKNOWN
Classifier: Framework :: Buildout
Classifier: Intended Audience :: Developers
Classifier: Topic :: Software Development :: Build Tools
Classifier: Topic :: Software Development :: Libraries :: Python Modules
